{
  "https://thediplomat.com/feed/": "https://thediplomat.com/2026/01/trumps-appointee-for-ambassador-to-vietnam-to-take-harder-line-on-trade/",
  "https://www.foreignaffairs.com/rss.xml": "1134397",
  "https://foreignpolicy.com/feed/": "https://foreignpolicy.com/?p=1217367",
  "https://evilgodfahim.github.io/ps/combined.xml": "https://www.project-syndicate.org/commentary/what-putin-thinks-of-the-us-operation-in-venezuela-by-nina-l-khrushcheva-2026-01",
  "https://evilgodfahim.github.io/eco/combined.xml": "https://archive.is/o/nuunc/https://www.economist.com/europe/2026/01/14/europe-has-three-options-for-defending-greenland",
  "https://www.eiu.com/n/feed/": "https://services.eiu.com/?p=20634",
  "https://www.lowyinstitute.org/the-interpreter/rss.xml": "41010",
  "https://geopoliticalfutures.com/feed/": "https://geopoliticalfutures.com/?p=422218"
}