{
  "https://thediplomat.com/feed/": "https://thediplomat.com/2025/12/myanmars-military-prepares-to-enact-its-election-plan/",
  "https://www.foreignaffairs.com/rss.xml": "1134304",
  "https://foreignpolicy.com/feed/": "https://foreignpolicy.com/?p=1215615",
  "https://evilgodfahim.github.io/ps/combined.xml": "https://www.project-syndicate.org/commentary/trump-affordability-problem-assigning-blame-by-michael-r-strain-2025-12",
  "https://evilgodfahim.github.io/eco/combined.xml": "https://archive.is/o/nuunc/https://www.economist.com/europe/2025/12/23/the-baltic-is-becoming-a-battleground-between-nato-and-russia",
  "https://www.eiu.com/n/feed/": "https://services.eiu.com/?p=20634",
  "https://www.lowyinstitute.org/the-interpreter/rss.xml": "40986",
  "https://geopoliticalfutures.com/feed/": "https://geopoliticalfutures.com/?p=420412"
}